develop/docker-bash.py
lxcraft/__init__.py
lxcraft/plan.py
lxcraft/resource.py
lxcraft/system.py
lxcraft/version.py
lxcraft/debian/__init__.py
lxcraft/debian/apt_package.py
lxcraft/path/__init__.py
lxcraft/path/directory.py
lxcraft/path/filecontent.py
lxcraft/python/__init__.py
lxcraft/python/pip_package.py
lxcraft/user/__init__.py
lxcraft/user/user.py
tests/test_apt_package.py
tests/test_directory.py
tests/test_filecontent.py
tests/test_pip_package.py
tests/test_plan.py
tests/test_resource.py
tests/test_user.py
tests/test_version.py
lxcraft-0.0.5.dist-info/LICENSE
lxcraft-0.0.5.dist-info/METADATA
lxcraft-0.0.5.dist-info/WHEEL
lxcraft-0.0.5.dist-info/entry_points.txt
lxcraft-0.0.5.dist-info/top_level.txt
lxcraft-0.0.5.dist-info/RECORD
