Metadata-Version: 2.1
Name: lxcraft
Version: 0.0.5
Summary: A simple declarative configuration build tool for Linux systems
Home-page: https://github.com/joaompinto/lxcraft
Author: João Pinto
Author-email: lamego.pinto@gmail.com
License: MIT
License-File: LICENSE
Requires-Dist: rich
Requires-Dist: taglogger
